Metadata-Version: 1.2
Name: hdre
Version: 1.1
Summary: generalized machine learning algorithm for complex loss functions and non-linear coefficients
Home-page: https://github.com/Freedomtowin/kernelml
Author: Rohan Kotwani
License: MIT
Keywords: high density region estimator - kernel machine learning nonlinear
Platform: UNKNOWN
Classifier: Development Status :: 4 - Beta
Classifier: Intended Audience :: Developers
Classifier: Intended Audience :: Science/Research
Classifier: Topic :: Software Development
Classifier: Topic :: Scientific/Engineering
Classifier: License :: OSI Approved :: MIT License
Classifier: Programming Language :: Python :: 3
Requires-Python: >=3.6
